{
    "err": 0,
    "msg": "success",
    "data": [
        {
            "name": "待发货订单",
            "num": "9"
        },
        {
            "name": "待回复客户数",
            "num": "0"
        },
        {
            "name": "近期滞销商品",
            "num": "10"
        },
        {
            "name": "待退款订单",
            "num": "0"
        },
        {
            "name": "排队中客户数",
            "num": "20"
        },
        {
            "name": "库存过少商品",
            "num": "3"
        }
    ]
}
